evaluation/2507.05257v2.pdf
evaluation/__init__.py
evaluation/accurate_retrieval_eval.py
evaluation/conflict_resolution_eval.py
evaluation/full_benchmark_eval.py
evaluation/long_range_understanding_eval.py
evaluation/test_time_learning_eval.py
evaluation/data/multihoprag_corpus.json
evaluation/data/multihoprag_qa.json
graphmem/__init__.py
graphmem/version.py
graphmem/context/__init__.py
graphmem/context/chunker.py
graphmem/context/context_engine.py
graphmem/context/extractors.py
graphmem/context/multimodal.py
graphmem/core/__init__.py
graphmem/core/exceptions.py
graphmem/core/memory.py
graphmem/core/memory_types.py
graphmem/evolution/__init__.py
graphmem/evolution/consolidation.py
graphmem/evolution/decay.py
graphmem/evolution/importance_scorer.py
graphmem/evolution/memory_evolution.py
graphmem/evolution/rehydration.py
graphmem/graph/__init__.py
graphmem/graph/community_detector.py
graphmem/graph/entity_resolver.py
graphmem/graph/knowledge_graph.py
graphmem/ingestion/__init__.py
graphmem/ingestion/async_extractor.py
graphmem/ingestion/auto_scale.py
graphmem/ingestion/batch_embedder.py
graphmem/ingestion/benchmark.py
graphmem/ingestion/pipeline.py
graphmem/llm/__init__.py
graphmem/llm/embeddings.py
graphmem/llm/providers.py
graphmem/retrieval/__init__.py
graphmem/retrieval/query_engine.py
graphmem/retrieval/retriever.py
graphmem/retrieval/semantic_search.py
graphmem/stores/__init__.py
graphmem/stores/memory_store.py
graphmem/stores/neo4j_store.py
graphmem/stores/redis_cache.py
graphmem/stores/turso_store.py
agentic_graph_mem-1.9.4.dist-info/METADATA
agentic_graph_mem-1.9.4.dist-info/WHEEL
agentic_graph_mem-1.9.4.dist-info/licenses/LICENSE
agentic_graph_mem-1.9.4.dist-info/RECORD
