Metadata-Version: 2.3
Name: agentic-graph-mem
Version: 1.9.4
Summary: Production-Grade Agent Memory Framework for Agentic AI
Project-URL: Homepage, https://github.com/ameerai/graphmem
Project-URL: Documentation, https://graphmem.readthedocs.io
Project-URL: Repository, https://github.com/ameerai/graphmem
Project-URL: Issues, https://github.com/ameerai/graphmem/issues
Author-email: Ameer AI <ameer@ameerai.com>
License: MIT
License-File: LICENSE
Keywords: agent,agentic-ai,ai,embedding,graphrag,knowledge-graph,llm,memory,neo4j,rag
Classifier: Development Status :: 4 - Beta
Classifier: Intended Audience :: Developers
Classifier: Intended Audience :: Science/Research
Classifier: License :: OSI Approved :: MIT License
Classifier: Operating System :: OS Independent
Classifier: Programming Language :: Python :: 3
Classifier: Programming Language :: Python :: 3.9
Classifier: Programming Language :: Python :: 3.10
Classifier: Programming Language :: Python :: 3.11
Classifier: Programming Language :: Python :: 3.12
Classifier: Topic :: Scientific/Engineering :: Artificial Intelligence
Classifier: Topic :: Software Development :: Libraries :: Python Modules
Requires-Python: >=3.9
Requires-Dist: networkx>=3.0
Requires-Dist: numpy>=1.21.0
Requires-Dist: pydantic>=2.0.0
Provides-Extra: all
Requires-Dist: anthropic>=0.25.0; extra == 'all'
Requires-Dist: beautifulsoup4>=4.12.0; extra == 'all'
Requires-Dist: libsql>=0.1.0; extra == 'all'
Requires-Dist: neo4j>=5.0.0; extra == 'all'
Requires-Dist: openai>=1.0.0; extra == 'all'
Requires-Dist: pillow>=9.0.0; extra == 'all'
Requires-Dist: psutil>=5.9.0; extra == 'all'
Requires-Dist: pymupdf>=1.23.0; extra == 'all'
Requires-Dist: pytesseract>=0.3.10; extra == 'all'
Requires-Dist: redis>=4.0.0; extra == 'all'
Requires-Dist: requests>=2.31.0; extra == 'all'
Requires-Dist: sentence-transformers>=2.2.0; extra == 'all'
Requires-Dist: torch>=2.0.0; extra == 'all'
Provides-Extra: anthropic
Requires-Dist: anthropic>=0.25.0; extra == 'anthropic'
Provides-Extra: audio
Requires-Dist: openai-whisper>=20231117; extra == 'audio'
Provides-Extra: dev
Requires-Dist: black>=23.0.0; extra == 'dev'
Requires-Dist: mypy>=1.0.0; extra == 'dev'
Requires-Dist: pytest-asyncio>=0.21.0; extra == 'dev'
Requires-Dist: pytest-cov>=4.0.0; extra == 'dev'
Requires-Dist: pytest>=7.0.0; extra == 'dev'
Requires-Dist: ruff>=0.1.0; extra == 'dev'
Provides-Extra: docs
Requires-Dist: beautifulsoup4>=4.12.0; extra == 'docs'
Requires-Dist: openai-whisper>=20231117; extra == 'docs'
Requires-Dist: pillow>=9.0.0; extra == 'docs'
Requires-Dist: pymupdf>=1.23.0; extra == 'docs'
Requires-Dist: pytesseract>=0.3.10; extra == 'docs'
Requires-Dist: requests>=2.31.0; extra == 'docs'
Provides-Extra: gpu
Requires-Dist: psutil>=5.9.0; extra == 'gpu'
Requires-Dist: torch>=2.0.0; extra == 'gpu'
Provides-Extra: libsql
Requires-Dist: libsql>=0.1.0; extra == 'libsql'
Provides-Extra: llm
Requires-Dist: anthropic>=0.25.0; extra == 'llm'
Requires-Dist: openai>=1.0.0; extra == 'llm'
Provides-Extra: local
Requires-Dist: sentence-transformers>=2.2.0; extra == 'local'
Provides-Extra: neo4j
Requires-Dist: neo4j>=5.0.0; extra == 'neo4j'
Provides-Extra: ocr
Requires-Dist: pillow>=9.0.0; extra == 'ocr'
Requires-Dist: pytesseract>=0.3.10; extra == 'ocr'
Provides-Extra: openai
Requires-Dist: openai>=1.0.0; extra == 'openai'
Provides-Extra: pdf
Requires-Dist: pymupdf>=1.23.0; extra == 'pdf'
Provides-Extra: redis
Requires-Dist: redis>=4.0.0; extra == 'redis'
Provides-Extra: storage
Requires-Dist: libsql>=0.1.0; extra == 'storage'
Requires-Dist: neo4j>=5.0.0; extra == 'storage'
Requires-Dist: redis>=4.0.0; extra == 'storage'
Provides-Extra: web
Requires-Dist: beautifulsoup4>=4.12.0; extra == 'web'
Requires-Dist: requests>=2.31.0; extra == 'web'
